garmin_workouts_mcp/__init__.py
garmin_workouts_mcp/garmin_workout.py
garmin_workouts_mcp/main.py
garmin_workouts_mcp-0.6.1.dist-info/licenses/LICENSE
tests/__init__.py
tests/test_garmin_workout.py
tests/test_integration.py
tests/test_main.py
garmin_workouts_mcp-0.6.1.dist-info/METADATA
garmin_workouts_mcp-0.6.1.dist-info/WHEEL
garmin_workouts_mcp-0.6.1.dist-info/entry_points.txt
garmin_workouts_mcp-0.6.1.dist-info/top_level.txt
garmin_workouts_mcp-0.6.1.dist-info/RECORD
