Metadata-Version: 2.4
Name: garmin-workouts-mcp
Version: 0.6.1
Summary: Garmin Workouts MCP Server
Author: Stev Witzel
License: MIT
Requires-Python: >=3.10
License-File: LICENSE
Requires-Dist: fastmcp>=2.9.1
Requires-Dist: garth>=0.5.17
Dynamic: license-file
